pybind11_pixelmatch/__init__.py
pybind11_pixelmatch/__main__.py
pybind11_pixelmatch/_core.pypy37-pp73-win_amd64.pyd
pybind11_pixelmatch-0.1.3.dist-info/METADATA
pybind11_pixelmatch-0.1.3.dist-info/WHEEL
pybind11_pixelmatch-0.1.3.dist-info/entry_points.txt
pybind11_pixelmatch-0.1.3.dist-info/licenses/LICENSE
pybind11_pixelmatch-0.1.3.dist-info/RECORD
