Metadata-Version: 2.1
Name: pybind11_pixelmatch
Version: 0.1.3
Summary: A C++17 port of the JavaScript pixelmatch library (with python binding), providing a small pixel-level image comparison library.
Author-Email: district10 <dvorak4tzx@gmail.com>
Classifier: Development Status :: 4 - Beta
Classifier: License :: OSI Approved :: MIT License
Classifier: Programming Language :: Python :: 3 :: Only
Classifier: Programming Language :: Python :: 3.7
Classifier: Programming Language :: Python :: 3.8
Classifier: Programming Language :: Python :: 3.9
Classifier: Programming Language :: Python :: 3.10
Classifier: Programming Language :: Python :: 3.11
Project-URL: Homepage, https://github.com/cubao/pybind11_pixelmatch
Requires-Python: >=3.7
Requires-Dist: numpy
Requires-Dist: opencv-python
Requires-Dist: pytest; extra == "test"
Provides-Extra: test
License-File: LICENSE
